{
"data": [
  {
    "id": 1,
    "roleName": "超级管理员",
    "roleDesc": "可管理所有权限",
    "children": [
      {
        "id": 101,
        "authName": "商品管理",
        "path": null,
        "children": [
          {
            "id": 104,
            "authName": "商品列表",
            "path": null,
            "children": [
              {
                "id": 105,
                "authName": "添加商品",
                "path": null
              },
              {
                "id": 106,
                "authName": "修改商品",
                "path": null
              },
              {
                "id": 107,
                "authName": "删除商品",
                "path": null
              }
            ]
          },
          {
            "id": 108,
            "authName": "分类参数",
            "path": null,
            "children": [
              {
                "id": 109,
                "authName": "获取参数列表",
                "path": null
              },
              {
                "id": 110,
                "authName": "创建分类参数",
                "path": null
              },
              {
                "id": 111,
                "authName": "删除分类参数",
                "path": null
              },
              {
                "id": 111,
                "authName": "更新分类参数",
                "path": null
              }
            ]
          }
        ]
      }
    ]
  },
  {
    "id": 2,
    "roleName": "管理员",
    "roleDesc": "可管理部分权限",
    "children": [
      {
        "id": 201,
        "authName": "商品管理",
        "path": null,
        "children": [
          {
            "id": 202,
            "authName": "商品列表",
            "path": null,
            "children": [
              {
                "id": 203,
                "authName": "添加商品",
                "path": null
              }
            ]
          },
          {
            "id": 204,
            "authName": "分类参数",
            "path": null,
            "children": [
              {
                "id": 205,
                "authName": "获取参数列表",
                "path": null
              },
              {
                "id": 206,
                "authName": "更新分类参数",
                "path": null
              }
            ]
          }
        ]
      }
    ]
  }
],
  "meta": {
    "msg": "获取成功",
    "status": 200
  }
}